gherald/__init__.py
gherald/__main__.py
gherald/data_pipeline.py
gherald/pydriller/__init__.py
gherald/pydriller/domain/commit.py
gherald/pydriller/domain/developer.py
gherald/pydriller/git.py
gherald/pydriller/metrics/process/change_set.py
gherald/pydriller/metrics/process/code_churn.py
gherald/pydriller/metrics/process/commits_count.py
gherald/pydriller/metrics/process/contributors_count.py
gherald/pydriller/metrics/process/contributors_experience.py
gherald/pydriller/metrics/process/history_complexity.py
gherald/pydriller/metrics/process/hunks_count.py
gherald/pydriller/metrics/process/lines_count.py
gherald/pydriller/metrics/process/process_metric.py
gherald/pydriller/repository.py
gherald/pydriller/utils/conf.py
gherald/risk_assessment.py
gherald-0.1.2.dist-info/LICENSE
gherald-0.1.2.dist-info/METADATA
gherald-0.1.2.dist-info/WHEEL
gherald-0.1.2.dist-info/entry_points.txt
gherald-0.1.2.dist-info/RECORD
