Metadata-Version: 2.1
Name: gherald
Version: 0.1.2
Summary: A python package to assess the risk of a change during code review.
Home-page: https://github.com/filipe-cogo/gherald
License: MIT
Author: University of Waterloo
Author-email: yuxueyao0130@gmail.com
Requires-Python: >=3.9,<3.13
Classifier: Development Status :: 3 - Alpha
Classifier: Intended Audience :: Developers
Classifier: License :: OSI Approved :: MIT License
Classifier: Operating System :: OS Independent
Classifier: Programming Language :: Python :: 3
Classifier: Programming Language :: Python :: 3.9
Classifier: Programming Language :: Python :: 3.10
Classifier: Programming Language :: Python :: 3.11
Classifier: Programming Language :: Python :: 3.12
Classifier: Topic :: Software Development :: Libraries :: Python Modules
Requires-Dist: GitPython (>=3.1.40,<4.0.0)
Requires-Dist: nltk (>=3.8.1,<4.0.0)
Requires-Dist: pandarallel (>=1.6.5,<2.0.0)
Requires-Dist: pandas (>=2.1.2,<3.0.0)
Requires-Dist: pydriller (>=2.5.1,<3.0.0)
Requires-Dist: rich (>=10.14.0,<11.0.0)
Requires-Dist: typer[all] (>=0.4.0,<0.5.0)
Project-URL: Repository, https://github.com/filipe-cogo/gherald
